perchance/__init__.py
perchance/errors.py
perchance/generator.py
perchance/imagegenerator.py
perchance/textgenerator.py
perchance/utils.py
perchance-0.1.0.dist-info/licenses/LICENSE
perchance-0.1.0.dist-info/METADATA
perchance-0.1.0.dist-info/WHEEL
perchance-0.1.0.dist-info/RECORD
