Metadata-Version: 2.4
Name: perchance
Version: 0.1.0
Summary: Unofficial Python API for Perchance.
License: MIT
License-File: LICENSE
Author: EeeMoon
Requires-Python: >=3.11,<4.0
Classifier: License :: OSI Approved :: MIT License
Classifier: Programming Language :: Python :: 3
Classifier: Programming Language :: Python :: 3.11
Classifier: Programming Language :: Python :: 3.12
Classifier: Programming Language :: Python :: 3.13
Classifier: Programming Language :: Python :: 3.14
Requires-Dist: aiofiles (>=25.1.0,<26.0.0)
Requires-Dist: playwright (>=1.57.0,<2.0.0)
Project-URL: Homepage, https://github.com/eeemoon/perchance
